pymatrix/__init__.py
pymatrix/pymatrix.py
pymatrix_rain-1.4.0.dist-info/licenses/LICENSE
pymatrix_rain-1.4.0.dist-info/METADATA
pymatrix_rain-1.4.0.dist-info/WHEEL
pymatrix_rain-1.4.0.dist-info/entry_points.txt
pymatrix_rain-1.4.0.dist-info/top_level.txt
pymatrix_rain-1.4.0.dist-info/RECORD
