Metadata-Version: 2.4
Name: pymatrix-rain
Version: 1.4.0
Summary: matrix rain using curses
Home-page: https://github.com/tech-chad/pymatrix
Author: Chad Larson
Author-email: techchad2@gmail.com
License: MIT
Classifier: Programming Language :: Python :: 3
Classifier: Programming Language :: Python :: 3 :: Only
Classifier: Programming Language :: Python :: 3.8
Classifier: Programming Language :: Python :: 3.9
Classifier: Programming Language :: Python :: 3.10
Classifier: Programming Language :: Python :: 3.11
Classifier: Programming Language :: Python :: 3.12
Requires-Python: >=3.8
License-File: LICENSE
Requires-Dist: windows-curses; sys_platform == "win32"
Dynamic: license-file
